fpastebin-1.0.0.dist-info/METADATA
fpastebin-1.0.0.dist-info/WHEEL
fpastebin-1.0.0.dist-info/metadata.json
fpastebin-1.0.0.dist-info/top_level.txt
fpastebin-1.0.0.dist-info/DESCRIPTION.rst
fpastebin-1.0.0.dist-info/RECORD
fpastebin/fpastebin.py
