Metadata-Version: 2.0
Name: fpastebin
Version: 1.0.0
Summary: A tool to upload text to http://paste.fedoraproject.org/
Home-page: http://github.com/surajssd/fpastebin
Author: Suraj Deshmukh
Author-email: surajssd009005@gmail.com
License: MIT
Platform: UNKNOWN
Requires-Dist: requests
